{
  "at": "2026-06-30",
  "source": "polymarket",
  "championship": {
    "ATL": 0.013,
    "BKN": 0.0105,
    "CHI": 0.0055,
    "DET": 0.031,
    "MIA": 0.0605,
    "NYK": 0.105,
    "PHI": 0.0115,
    "WAS": 0.0155,
    "DEN": 0.0405,
    "HOU": 0.013,
    "LAL": 0.0265,
    "MIN": 0.0345,
    "OKC": 0.22,
    "POR": 0.0155,
    "IND": 0.02,
    "MIL": 0.0065,
    "ORL": 0.0125,
    "TOR": 0.0275,
    "DAL": 0.009,
    "GSW": 0.0575,
    "LAC": 0.0135,
    "MEM": 0.0085,
    "NOP": 0.0055,
    "PHX": 0.0105,
    "SAS": 0.18,
    "BOS": 0.065,
    "CLE": 0.022,
    "SAC": 0.0115,
    "UTA": 0.0115
  },
  "eastConf": {},
  "westConf": {}
}